fireblocks_client/__init__.py
fireblocks_client/api_client.py
fireblocks_client/configuration.py
fireblocks_client/exceptions.py
fireblocks_client/rest.py
fireblocks_client/schemas.py
fireblocks_client/apis/__init__.py
fireblocks_client/apis/path_to_api.py
fireblocks_client/apis/tag_to_api.py
fireblocks_client/apis/paths/__init__.py
fireblocks_client/apis/paths/audits.py
fireblocks_client/apis/paths/connections.py
fireblocks_client/apis/paths/connections_wc.py
fireblocks_client/apis/paths/connections_wc_id.py
fireblocks_client/apis/paths/contracts.py
fireblocks_client/apis/paths/contracts_contract_id.py
fireblocks_client/apis/paths/contracts_contract_id_asset_id.py
fireblocks_client/apis/paths/estimate_network_fee.py
fireblocks_client/apis/paths/exchange_accounts.py
fireblocks_client/apis/paths/exchange_accounts_exchange_account_id.py
fireblocks_client/apis/paths/exchange_accounts_exchange_account_id_asset_id.py
fireblocks_client/apis/paths/exchange_accounts_exchange_account_id_convert.py
fireblocks_client/apis/paths/exchange_accounts_exchange_account_id_internal_transfer.py
fireblocks_client/apis/paths/external_wallets.py
fireblocks_client/apis/paths/external_wallets_wallet_id.py
fireblocks_client/apis/paths/external_wallets_wallet_id_asset_id.py
fireblocks_client/apis/paths/external_wallets_wallet_id_set_customer_ref_id.py
fireblocks_client/apis/paths/fiat_accounts.py
fireblocks_client/apis/paths/fiat_accounts_account_id.py
fireblocks_client/apis/paths/fiat_accounts_account_id_deposit_from_linked_dda.py
fireblocks_client/apis/paths/fiat_accounts_account_id_redeem_to_linked_dda.py
fireblocks_client/apis/paths/gas_station.py
fireblocks_client/apis/paths/gas_station_asset_id.py
fireblocks_client/apis/paths/gas_station_configuration.py
fireblocks_client/apis/paths/gas_station_configuration_asset_id.py
fireblocks_client/apis/paths/internal_wallets.py
fireblocks_client/apis/paths/internal_wallets_wallet_id.py
fireblocks_py-1.0.0.dist-info/METADATA
fireblocks_py-1.0.0.dist-info/WHEEL
fireblocks_py-1.0.0.dist-info/top_level.txt
fireblocks_py-1.0.0.dist-info/RECORD
